datakitpy/__init__.py
datakitpy/datakit.py
datakitpy/helpers.py
datakitpy/resources.py
datastudio_lib-0.2.2.dist-info/LICENSE
datastudio_lib-0.2.2.dist-info/METADATA
datastudio_lib-0.2.2.dist-info/WHEEL
datastudio_lib-0.2.2.dist-info/top_level.txt
datastudio_lib-0.2.2.dist-info/RECORD
