Metadata-Version: 2.1
Name: datastudio-lib
Version: 0.2.2
Summary: DataStudio Python library
Author-email: echus <varvara@echus.co>
Requires-Python: >=3.11
License-File: LICENSE
Requires-Dist: pandas<3.0,>=2.2
Requires-Dist: docker<8,>=7.1.0
Provides-Extra: all
Requires-Dist: datastudio-lib[development]; extra == "all"
Provides-Extra: development
Requires-Dist: pre-commit; extra == "development"
Requires-Dist: build; extra == "development"
